<?xml version="1.0"?>

<precice-configuration>

    <log>
        <sink type="stream" output="stdout" filter="%Severity% > debug" enabled="true"/>
    </log>

    <solver-interface dimensions="3">

    <data:scalar name="Temperature"/>
    <data:scalar name="Heat-Flux"/>

    <mesh name="F2-to-Solid-Mesh">
        <use-data name="Temperature"/>
        <use-data name="Heat-Flux"/>
    </mesh>

    <mesh name="Solid-to-F2-Mesh">
        <use-data name="Temperature"/>
        <use-data name="Heat-Flux"/>
    </mesh>

    <participant name="Fluid2">
        <use-mesh name="F2-to-Solid-Mesh" provide="yes"/>
        <read-data name="Heat-Flux" mesh="F2-to-Solid-Mesh"/>
        <write-data name="Temperature" mesh="F2-to-Solid-Mesh"/>
    </participant>

    <participant name="Solid">
        <use-mesh name="F2-to-Solid-Mesh" from="Fluid2"/>
        <use-mesh name="Solid-to-F2-Mesh" provide="yes"/>
        <read-data name="Temperature" mesh="Solid-to-F2-Mesh"/>
        <write-data name="Heat-Flux" mesh="Solid-to-F2-Mesh"/>
        <mapping:nearest-neighbor direction="read" from="F2-to-Solid-Mesh" to="Solid-to-F2-Mesh" constraint="consistent" timing="initial"/>
        <mapping:nearest-neighbor direction="write" from="Solid-to-F2-Mesh" to="F2-to-Solid-Mesh" constraint="consistent" timing="initial"/>
    </participant>

    <m2n:sockets from="Fluid2" to="Solid" distribution-type="gather-scatter"/>

    <coupling-scheme:serial-implicit>
      <max-timesteps value="4000" />
      <timestep-length value="0.001"/>
      <max-iterations value="2000" />
      <participants first="Fluid2" second="Solid" />
      <min-iteration-convergence-measure min-iterations="1" data="Temperature" mesh="F2-to-Solid-Mesh"/>
        <exchange data="Heat-Flux" mesh="F2-to-Solid-Mesh" from="Solid" to="Fluid2"/>
        <exchange data="Temperature" mesh="F2-to-Solid-Mesh" from="Fluid2" to="Solid"/>
    </coupling-scheme:serial-implicit>

    </solver-interface>

</precice-configuration>
